iwanna/__init__.py
iwanna/__main__.py
iwanna/__version__.py
iwanna/app.py
iwanna/config.py
iwanna/format.py
iwanna/py.typed
iwanna-1.0.0.dist-info/LICENSE
iwanna-1.0.0.dist-info/METADATA
iwanna-1.0.0.dist-info/WHEEL
iwanna-1.0.0.dist-info/entry_points.txt
iwanna-1.0.0.dist-info/RECORD
